Metadata-Version: 1.0
Name: uvspotify
Version: 0.4
Summary: Spotify client for uvhttp
Home-page: https://github.com/justinbarrick/uvspotify
Author: UNKNOWN
Author-email: UNKNOWN
License: UNKNOWN
Platform: UNKNOWN
